MANIFEST.in
README.rst
setup.py
docs/HISTORY.txt
docs/INSTALL.txt
docs/LICENSE.GPL
docs/LICENSE.txt
simplelayout/__init__.py
simplelayout.ui.base.egg-info/PKG-INFO
simplelayout.ui.base.egg-info/SOURCES.txt
simplelayout.ui.base.egg-info/dependency_links.txt
simplelayout.ui.base.egg-info/entry_points.txt
simplelayout.ui.base.egg-info/namespace_packages.txt
simplelayout.ui.base.egg-info/not-zip-safe
simplelayout.ui.base.egg-info/requires.txt
simplelayout.ui.base.egg-info/top_level.txt
simplelayout/ui/__init__.py
simplelayout/ui/base/__init__.py
simplelayout/ui/base/config.py
simplelayout/ui/base/configure.zcml
simplelayout/ui/base/testing.py
simplelayout/ui/base/upgrades.py
simplelayout/ui/base/upgrades.zcml
simplelayout/ui/base/Extensions/__init__.py
simplelayout/ui/base/Extensions/install.py
simplelayout/ui/base/browser/__init__.py
simplelayout/ui/base/browser/configure.zcml
simplelayout/ui/base/browser/content.pt
simplelayout/ui/base/browser/delete_confirmation.pt
simplelayout/ui/base/browser/locked_information.pt
simplelayout/ui/base/browser/sl-colorbox.py
simplelayout/ui/base/browser/views.py
simplelayout/ui/base/browser/resources/jq-QueuManagerPlugin-v0.2.js
simplelayout/ui/base/browser/resources/sl-base-general.js
simplelayout/ui/base/browser/resources/sl-base-styles.css
simplelayout/ui/base/browser/resources/sl-base.js
simplelayout/ui/base/browser/resources/theme/ui.accordion.css
simplelayout/ui/base/browser/resources/theme/ui.all.css
simplelayout/ui/base/browser/resources/theme/ui.base.css
simplelayout/ui/base/browser/resources/theme/ui.core.css
simplelayout/ui/base/browser/resources/theme/ui.datepicker.css
simplelayout/ui/base/browser/resources/theme/ui.dialog.css
simplelayout/ui/base/browser/resources/theme/ui.progressbar.css
simplelayout/ui/base/browser/resources/theme/ui.resizable.css
simplelayout/ui/base/browser/resources/theme/ui.slider.css
simplelayout/ui/base/browser/resources/theme/ui.tabs.css
simplelayout/ui/base/browser/resources/theme/ui.theme.css
simplelayout/ui/base/browser/resources/theme/images/ui-bg_flat_0_aaaaaa_40x100.png
simplelayout/ui/base/browser/resources/theme/images/ui-bg_flat_75_ffffff_40x100.png
simplelayout/ui/base/browser/resources/theme/images/ui-bg_glass_55_fbf9ee_1x400.png
simplelayout/ui/base/browser/resources/theme/images/ui-bg_glass_65_ffffff_1x400.png
