Metadata-Version: 1.1
Name: simplelayout.ui.base
Version: 3.0.6
Summary: Simplelayout ui base package - for plone
Home-page: https://github.com/4teamwork/simplelayout.ui.base
Author: 4teamwork AG
Author-email: mailto:info@4teamwork.ch
License: GPL2
Platform: UNKNOWN
Classifier: Framework :: Plone
Classifier: Programming Language :: Python
Classifier: Topic :: Software Development :: Libraries :: Python Modules
